{
  "level": 2,
  "title": "CN Level 2 — OSI & TCP/IP Models",
  "concept": "Layered architecture, OSI 7-layer model, TCP/IP model and mapping protocols to layers.",
  "type": "MCQ",
  "challenges": [
    {
      "id": 1,
      "question": "The OSI reference model has:",
      "options": {
        "A": "4 layers",
        "B": "5 layers",
        "C": "7 layers",
        "D": "8 layers"
      },
      "answer": "C",
      "explanation": "The OSI model defines 7 layers from Physical up to Application."
    },
    {
      "id": 2,
      "question": "The TCP/IP reference model typically has:",
      "options": {
        "A": "2 layers",
        "B": "3 layers",
        "C": "4 layers",
        "D": "7 layers"
      },
      "answer": "C",
      "explanation": "The TCP/IP model is commonly represented with 4 layers: Link, Internet, Transport, Application."
    },
    {
      "id": 3,
      "question": "In the OSI/TCP-IP models, HTTP is considered an example of a protocol at the:",
      "options": {
        "A": "Physical layer",
        "B": "Network layer",
        "C": "Transport layer",
        "D": "Application layer"
      },
      "answer": "D",
      "explanation": "HTTP is an Application layer protocol used for web communication."
    },
    {
      "id": 4,
      "question": "Which of the following lists OSI layers in the correct order from bottom (closest to hardware) to top (closest to user)?",
      "options": {
        "A": "Physical, Data Link, Network, Transport, Session, Presentation, Application",
        "B": "Application, Presentation, Session, Transport, Network, Data Link, Physical",
        "C": "Data Link, Physical, Network, Transport, Session, Presentation, Application",
        "D": "Network, Data Link, Physical, Transport, Session, Presentation, Application"
      },
      "answer": "A",
      "explanation": "OSI layers from bottom to top are: Physical, Data Link, Network, Transport, Session, Presentation, Application."
    },
    {
      "id": 5,
      "question": "Which service is primarily provided by the transport layer to the upper layers?",
      "options": {
        "A": "Routing between networks",
        "B": "End-to-end process-to-process communication",
        "C": "Physical signalling over the medium",
        "D": "Name to IP address resolution"
      },
      "answer": "B",
      "explanation": "The transport layer provides logical end-to-end communication between processes on different hosts."
    }
  ]
}
